mjcf_urdf_simple_converter/__init__.py
mjcf_urdf_simple_converter/mjcf_urdf_simple_converter.py
mjcf_urdf_simple_converter-0.7.2.dist-info/METADATA
mjcf_urdf_simple_converter-0.7.2.dist-info/WHEEL
mjcf_urdf_simple_converter-0.7.2.dist-info/licenses/LICENSE
mjcf_urdf_simple_converter-0.7.2.dist-info/RECORD
